{"id":6089772474099588,"sheetId":921940333488004,"rowNumber":1,"version":75,"cells":[{"columnId":4907304240867204,"type":"TEXT_NUMBER","value":"Cell1","displayValue":"Cell1"},{"columnId":2655504427181956,"type":"TEXT_NUMBER","value":"Cell2","displayValue":"Cell2"},{"columnId":7159104054552452,"type":"TEXT_NUMBER","value":"cell3","displayValue":"cell3"},{"columnId":6033204147709828,"type":"CHECKBOX","value":true},{"columnId":3781404334024580,"type":"CONTACT_LIST","value":"a@batie.com","displayValue":"Test Account"},{"columnId":7713278383155076,"type":"DATE","value":"2014-03-13"},{"columnId":2083778848941956,"type":"PICKLIST","value":"a","displayValue":"a"},{"columnId":6587378476312452,"type":"CHECKBOX","value":true}],"expanded":true,"accessLevel":"OWNER","createdAt":"2014-02-19T10:09:00-08:00","modifiedAt":"2014-03-14T08:34:34-07:00"}